pyPasswordGenerator/__init__.py
pyPasswordGenerator/password.py
pyPasswordGenerator-1.0.2.dist-info/LICENSE
pyPasswordGenerator-1.0.2.dist-info/METADATA
pyPasswordGenerator-1.0.2.dist-info/WHEEL
pyPasswordGenerator-1.0.2.dist-info/entry_points.txt
pyPasswordGenerator-1.0.2.dist-info/top_level.txt
pyPasswordGenerator-1.0.2.dist-info/RECORD
