Metadata-Version: 2.1
Name: pyPasswordGenerator
Version: 1.0.2
Summary: create random password with varies passcode set
Home-page: https://github.com/cove9988/PasswordGenerator
Author: Paulguo
Author-email: cove9988@gmail.com
License: MIT
Keywords: random password generator different lengths with customized character set
Platform: UNKNOWN
Classifier: Development Status :: 5 - Production/Stable
Classifier: Intended Audience :: Information Technology
Classifier: License :: OSI Approved :: MIT License
Classifier: Natural Language :: English
Classifier: Programming Language :: Python :: 3
Classifier: Programming Language :: Python :: 3.5
Classifier: Programming Language :: Python :: 3.6
Classifier: Programming Language :: Python :: 3.7
Classifier: Topic :: Utilities
Classifier: Operating System :: POSIX
